LICENSE.txt
MANIFEST.in
README.rst
requirements.txt
setup.cfg
setup.py
doc/Makefile
doc/make.bat
doc/source/about.rst
doc/source/conf.py
doc/source/examples.rst
doc/source/index.rst
doc/source/installation.rst
doc/source/refernce.rst
stuweparser/__init__.py
stuweparser/crawler.py
stuweparser/parser.py
stuweparser/xml_generator.py
stuweparser.egg-info/PKG-INFO
stuweparser.egg-info/SOURCES.txt
stuweparser.egg-info/dependency_links.txt
stuweparser.egg-info/requires.txt
stuweparser.egg-info/top_level.txt
stuweparser/__pycache__/__init__.cpython-35.pyc
stuweparser/__pycache__/__init__.cpython-36.pyc
stuweparser/__pycache__/crawler.cpython-35.pyc
stuweparser/__pycache__/crawler.cpython-36.pyc
stuweparser/__pycache__/parser.cpython-35.pyc
stuweparser/__pycache__/parser.cpython-36.pyc