Metadata-Version: 1.1
Name: stuweparser
Version: 0.1.1
Summary: Python package to parse menues from www.my-stuwe.de
Home-page: https://github.com/Trybnetic/stuweparser
Author: Marc Weitz, Steffen Lindner
Author-email: stuweparser@marc-weitz.de
License: MIT
Platform: Linux
Classifier: Development Status :: 3 - Alpha
Classifier: Environment :: Console
Classifier: License :: OSI Approved :: MIT License
Classifier: Operating System :: POSIX :: Linux
Classifier: Programming Language :: Python
Classifier: Programming Language :: Python :: 3.4
Classifier: Programming Language :: Python :: 3.5
Classifier: Programming Language :: Python :: 3.6
Classifier: Programming Language :: Python :: 3 :: Only
